franken/__init__.py
franken/config.py
franken/autotune/__init__.py
franken/autotune/__main__.py
franken/autotune/cli.py
franken/autotune/script.py
franken/backbones/__init__.py
franken/backbones/cli.py
franken/backbones/registry.json
franken/backbones/update_mace_registry.py
franken/backbones/utils.py
franken/backbones/wrappers/__init__.py
franken/backbones/wrappers/common_patches.py
franken/backbones/wrappers/fairchem_schnet.py
franken/backbones/wrappers/mace_wrap.py
franken/backbones/wrappers/sevenn.py
franken/calculators/__init__.py
franken/calculators/ase_calc.py
franken/calculators/lammps_calc.py
franken/data/__init__.py
franken/data/base.py
franken/data/distributed_sampler.py
franken/data/fairchem.py
franken/data/mace.py
franken/data/sevenn.py
franken/datasets/__init__.py
franken/datasets/registry.py
franken/datasets/PtH2O/pth2o_dataset.py
franken/datasets/TM23/tm23_dataset.py
franken/datasets/test/long.xyz
franken/datasets/test/md.xyz
franken/datasets/test/test.xyz
franken/datasets/test/test_dataset.py
franken/datasets/test/train.xyz
franken/datasets/test/validation.xyz
franken/datasets/water/HH_digitizer.csv
franken/datasets/water/OH_digitizer.csv
franken/datasets/water/OO_digitizer.csv
franken/datasets/water/exp_rdf.csv
franken/datasets/water/water_dataset.py
franken/metrics/__init__.py
franken/metrics/base.py
franken/metrics/functions.py
franken/metrics/registry.py
franken/rf/__init__.py
franken/rf/atomic_energies.py
franken/rf/heads.py
franken/rf/model.py
franken/rf/scaler.py
franken/trainers/__init__.py
franken/trainers/base.py
franken/trainers/log_utils.py
franken/trainers/rf_cuda_lowmem.py
franken/utils/__init__.py
franken/utils/distributed.py
franken/utils/file_utils.py
franken/utils/hostlist.py
franken/utils/jac.py
franken/utils/misc.py
franken/utils/linalg/__init__.py
franken/utils/linalg/cov.py
franken/utils/linalg/psdsolve.py
franken/utils/linalg/tri.py
franken-0.4.3.dist-info/METADATA
franken-0.4.3.dist-info/WHEEL
franken-0.4.3.dist-info/entry_points.txt
franken-0.4.3.dist-info/licenses/LICENSE.txt
franken-0.4.3.dist-info/RECORD
