Metadata-Version: 2.4
Name: franken
Version: 0.4.3
Summary: Franken fine-tuning scheme for ML potentials
Project-URL: Homepage, https://franken.readthedocs.io/
Project-URL: Documentation, https://franken.readthedocs.io/
Project-URL: Repository, https://github.com/CSML-IIT-UCL/franken
Author: Giacomo Meanti, Luigi Bonati, Pedro Juan Buigues Jorro
Author-email: Pietro Novelli <pietronvll@gmail.com>
License-Expression: MIT
License-File: LICENSE.txt
Keywords: franken,molecular dynamics,potentials
Classifier: Development Status :: 4 - Beta
Classifier: Intended Audience :: Science/Research
Classifier: License :: OSI Approved :: MIT License
Classifier: Programming Language :: Python :: 3.10
Classifier: Programming Language :: Python :: 3.11
Classifier: Programming Language :: Python :: 3.12
Requires-Python: >=3.10
Requires-Dist: ase
Requires-Dist: docstring-parser
Requires-Dist: e3nn
Requires-Dist: numpy
Requires-Dist: omegaconf
Requires-Dist: psutil
Requires-Dist: requests
Requires-Dist: scipy
Requires-Dist: torch>=2.4.0
Requires-Dist: tqdm
Provides-Extra: cuda
Requires-Dist: cupy; extra == 'cuda'
Provides-Extra: develop
Requires-Dist: black~=24.0; extra == 'develop'
Requires-Dist: packaging; extra == 'develop'
Requires-Dist: pre-commit; extra == 'develop'
Requires-Dist: pytest; extra == 'develop'
Requires-Dist: ruff; extra == 'develop'
Provides-Extra: docs
Requires-Dist: myst-parser; extra == 'docs'
Requires-Dist: nbsphinx; extra == 'docs'
Requires-Dist: sphinx; extra == 'docs'
Requires-Dist: sphinx-argparse; extra == 'docs'
Requires-Dist: sphinxawesome-theme; extra == 'docs'
Requires-Dist: sphinxcontrib-applehelp; extra == 'docs'
Requires-Dist: sphinxcontrib-devhelp; extra == 'docs'
Requires-Dist: sphinxcontrib-htmlhelp; extra == 'docs'
Requires-Dist: sphinxcontrib-jsmath; extra == 'docs'
Requires-Dist: sphinxcontrib-qthelp; extra == 'docs'
Requires-Dist: sphinxcontrib-serializinghtml; extra == 'docs'
Provides-Extra: fairchem
Requires-Dist: fairchem-core==1.10; extra == 'fairchem'
Provides-Extra: mace
Requires-Dist: mace-torch>=0.3.10; extra == 'mace'
Provides-Extra: sevenn
Requires-Dist: sevenn~=0.11; extra == 'sevenn'
